bin/km3net-detector
include/km3net/detector/datx.h
include/km3net/detector/detector.h
include/km3net/detector/detx.h
include/km3net/detector/json.h
km3detector/__init__.py
km3detector/km3detector_ext.cpython-39-x86_64-linux-gnu.so
km3detector/libkm3net_detector.so
lib/libkm3net_detector.so
lib/cmake/km3net-detector/km3net-detector-config.cmake
lib/cmake/km3net-detector/km3net-detector-release.cmake
lib/cmake/km3net-detector/km3net-detector.cmake
km3detector-0.1.0.dist-info/METADATA
km3detector-0.1.0.dist-info/WHEEL
km3detector-0.1.0.dist-info/RECORD
