Metadata-Version: 2.1
Name: km3detector
Version: 0.1.0
Summary: KM3NeT detector I/O library with nanobind Python bindings
Author-Email: Laurent Aphecetche <laurent.aphecetche@gmail.com>
License: BSD-3
Project-URL: Homepage, https://git.km3net.de/laphecetche/detector
Requires-Python: >=3.9
